frogml_cli/__init__.py
frogml_cli/cli.py
frogml_cli/commands/__init__.py
frogml_cli/commands/_logic/__init__.py
frogml_cli/commands/_logic/tools.py
frogml_cli/commands/alerts/__init__.py
frogml_cli/commands/alerts/alerts_commnad_group.py
frogml_cli/commands/alerts/delete/__init__.py
frogml_cli/commands/alerts/delete/_logic.py
frogml_cli/commands/alerts/delete/ui.py
frogml_cli/commands/alerts/list/__init__.py
frogml_cli/commands/alerts/list/_logic.py
frogml_cli/commands/alerts/list/ui.py
frogml_cli/commands/alerts/register/__init__.py
frogml_cli/commands/alerts/register/_logic.py
frogml_cli/commands/alerts/register/ui.py
frogml_cli/commands/audience/__init__.py
frogml_cli/commands/audience/_logic/__init__.py
frogml_cli/commands/audience/_logic/config/__init__.py
frogml_cli/commands/audience/_logic/config/config_base.py
frogml_cli/commands/audience/_logic/config/parser.py
frogml_cli/commands/audience/_logic/config/v1/__init__.py
frogml_cli/commands/audience/_logic/config/v1/audience_config.py
frogml_cli/commands/audience/_logic/config/v1/conditions_config.py
frogml_cli/commands/audience/_logic/config/v1/config_v1.py
frogml_cli/commands/audience/_logic/config/v1/route_config.py
frogml_cli/commands/audience/_logic/config/v1/spec.py
frogml_cli/commands/audience/audience_api_dump.py
frogml_cli/commands/audience/audience_commands_group.py
frogml_cli/commands/audience/create/__init__.py
frogml_cli/commands/audience/create/logic.py
frogml_cli/commands/audience/create/ui.py
frogml_cli/commands/audience/delete/__init__.py
frogml_cli/commands/audience/delete/logic.py
frogml_cli/commands/audience/delete/ui.py
frogml_cli/commands/audience/get/__init__.py
frogml_cli/commands/audience/get/logic.py
frogml_cli/commands/audience/get/ui.py
frogml_cli/commands/audience/list/__init__.py
frogml_cli/commands/audience/list/logic.py
frogml_cli/commands/audience/list/ui.py
frogml_cli/commands/audience/update/__init__.py
frogml_cli/commands/audience/update/logic.py
frogml_cli-0.1.1.dist-info/METADATA
frogml_cli-0.1.1.dist-info/WHEEL
frogml_cli-0.1.1.dist-info/entry_points.txt
frogml_cli-0.1.1.dist-info/RECORD
